galore/__init__.py
galore/cross_sections.py
galore/formats.py
galore/plot.py
galore/cli/__init__.py
galore/cli/galore.py
galore/cli/galore_get_cs.py
galore/cli/galore_plot_cs.py
galore/cli/utils.py
galore/data/cross_sections.json
galore/data/cross_sections_haxpes.json
galore/data/cross_sections_ups.json
galore/data/scofield_data.db
galore-0.9.2.dist-info/LICENSE
galore-0.9.2.dist-info/METADATA
galore-0.9.2.dist-info/WHEEL
galore-0.9.2.dist-info/entry_points.txt
galore-0.9.2.dist-info/top_level.txt
galore-0.9.2.dist-info/RECORD
